DebuggingLibrary/DebuggingLibrary.py
DebuggingLibrary/__init__.py
mpjp_debuggingLibrary-1.0.0.dist-info/METADATA
mpjp_debuggingLibrary-1.0.0.dist-info/RECORD
mpjp_debuggingLibrary-1.0.0.dist-info/WHEEL
mpjp_debuggingLibrary-1.0.0.dist-info/top_level.txt
